eventio/__init__.py
eventio/_version.py
eventio/base.py
eventio/constants.py
eventio/exceptions.py
eventio/file_types.py
eventio/header.cp313-win_amd64.pyd
eventio/header.pyx
eventio/histograms.py
eventio/search_utils.py
eventio/tools.py
eventio/var_int.cp313-win_amd64.pyd
eventio/var_int.pyx
eventio/version.py
eventio/version_handling.py
eventio/iact/__init__.py
eventio/iact/objects.py
eventio/scripts/__init__.py
eventio/scripts/cut_eventio_file.py
eventio/scripts/plot_hists.py
eventio/scripts/print_object_information.py
eventio/scripts/print_simtel_history.py
eventio/scripts/print_simtel_metaparams.py
eventio/scripts/print_structure.py
eventio/simtel/__init__.py
eventio/simtel/objects.py
eventio/simtel/parsing.cp313-win_amd64.pyd
eventio/simtel/parsing.pyx
eventio/simtel/pixelset.py
eventio/simtel/runheader_dtypes.py
eventio/simtel/simtelfile.py
eventio-2.0.0.dist-info/licenses/LICENSE.txt
eventio-2.0.0.dist-info/METADATA
eventio-2.0.0.dist-info/WHEEL
eventio-2.0.0.dist-info/entry_points.txt
eventio-2.0.0.dist-info/top_level.txt
eventio-2.0.0.dist-info/RECORD
