Metadata-Version: 2.4
Name: eventio
Version: 2.0.0
Summary: Python read-only implementation of the EventIO file format
Author-email: Maximilian Linhoff <maximilian.linhoff@tu-dortmund.de>, Dominik Neise <dominik.neise@cta-observatory.org>, Orel Gueta <orel.gueta@desy.de>
License: MIT
Project-URL: repository, https://github.com/cta-observatory/pyeventio
Project-URL: issues, https://github.com/cta-observatory/pyeventio/issues
Project-URL: conda-forge, https://anaconda.org/conda-forge/eventio
Classifier: Development Status :: 5 - Production/Stable
Classifier: Intended Audience :: Science/Research
Classifier: License :: OSI Approved :: MIT License
Classifier: Natural Language :: English
Classifier: Operating System :: OS Independent
Classifier: Programming Language :: Python
Classifier: Programming Language :: Python :: 3
Classifier: Programming Language :: Python :: 3.10
Classifier: Programming Language :: Python :: 3.11
Classifier: Programming Language :: Python :: 3.12
Classifier: Programming Language :: Python :: 3.13
Classifier: Programming Language :: Python :: 3 :: Only
Classifier: Topic :: Scientific/Engineering :: Astronomy
Classifier: Topic :: Scientific/Engineering :: Physics
Requires-Python: >=3.10
License-File: LICENSE.txt
Requires-Dist: numpy>=1.21
Requires-Dist: corsikaio<0.6.0,>=0.3.3
Requires-Dist: zstandard>0.11.1
Provides-Extra: test
Requires-Dist: pytest; extra == "test"
Provides-Extra: examples
Requires-Dist: astropy<8.0.0a0,>=5.3; extra == "examples"
Requires-Dist: ctapipe~=0.24.0; extra == "examples"
Requires-Dist: matplotlib; extra == "examples"
Provides-Extra: dev
Requires-Dist: setuptools_scm; extra == "dev"
Provides-Extra: all
Requires-Dist: eventio[dev,test]; extra == "all"
Dynamic: license-file
